cetus/__init__.py
cetus/cli.py
cetus/client.py
cetus/config.py
cetus/exceptions.py
cetus/formatters.py
cetus/markers.py
cetus/py.typed
cetus_client-0.0.3.dist-info/METADATA
cetus_client-0.0.3.dist-info/WHEEL
cetus_client-0.0.3.dist-info/entry_points.txt
cetus_client-0.0.3.dist-info/licenses/LICENSE
cetus_client-0.0.3.dist-info/RECORD
