Metadata-Version: 2.4
Name: cetus-client
Version: 0.0.3
Summary: CLI client for the Cetus threat intelligence alerting API
Project-URL: Homepage, https://alerting.sparkits.ca
Project-URL: Repository, https://github.com/SparkITSolutions/cetus-client
Project-URL: Changelog, https://github.com/SparkITSolutions/cetus-client/blob/main/CHANGELOG.md
Author: SparkIT
License-Expression: MIT
License-File: LICENSE
Keywords: alerting,dns,security,threat-intelligence
Classifier: Development Status :: 3 - Alpha
Classifier: Environment :: Console
Classifier: Intended Audience :: Information Technology
Classifier: Intended Audience :: System Administrators
Classifier: License :: OSI Approved :: MIT License
Classifier: Operating System :: OS Independent
Classifier: Programming Language :: Python :: 3
Classifier: Programming Language :: Python :: 3.10
Classifier: Programming Language :: Python :: 3.11
Classifier: Programming Language :: Python :: 3.12
Classifier: Programming Language :: Python :: 3.13
Classifier: Topic :: Security
Requires-Python: >=3.10
Requires-Dist: click<9,>=8.1
Requires-Dist: httpx<1,>=0.25
Requires-Dist: platformdirs<5,>=4.0
Requires-Dist: rich<14,>=13.0
Requires-Dist: tomli<3,>=2.0; python_version < '3.11'
Provides-Extra: dev
Requires-Dist: build>=1.0; extra == 'dev'
Requires-Dist: pyinstaller>=6.0; extra == 'dev'
Requires-Dist: pytest-asyncio>=0.23; extra == 'dev'
Requires-Dist: pytest-cov>=4.0; extra == 'dev'
Requires-Dist: pytest-httpx>=0.30; extra == 'dev'
Requires-Dist: pytest-timeout>=2.0; extra == 'dev'
Requires-Dist: pytest>=7.0; extra == 'dev'
Requires-Dist: ruff>=0.1; extra == 'dev'
